odoo/addons/product_standard_margin/README.rst
odoo/addons/product_standard_margin/__init__.py
odoo/addons/product_standard_margin/__manifest__.py
odoo/addons/product_standard_margin/i18n/de.po
odoo/addons/product_standard_margin/i18n/es.po
odoo/addons/product_standard_margin/i18n/fr.po
odoo/addons/product_standard_margin/i18n/it.po
odoo/addons/product_standard_margin/i18n/nl.po
odoo/addons/product_standard_margin/i18n/product_standard_margin.pot
odoo/addons/product_standard_margin/i18n/pt.po
odoo/addons/product_standard_margin/i18n/pt_BR.po
odoo/addons/product_standard_margin/models/__init__.py
odoo/addons/product_standard_margin/models/product_product.py
odoo/addons/product_standard_margin/models/product_template.py
odoo/addons/product_standard_margin/readme/CONTRIBUTORS.md
odoo/addons/product_standard_margin/readme/DESCRIPTION.md
odoo/addons/product_standard_margin/readme/ROADMAP.md
odoo/addons/product_standard_margin/static/description/icon.png
odoo/addons/product_standard_margin/static/description/index.html
odoo/addons/product_standard_margin/static/description/product_form.png
odoo/addons/product_standard_margin/tests/__init__.py
odoo/addons/product_standard_margin/tests/test_module.py
odoo/addons/product_standard_margin/views/view_product_product.xml
odoo/addons/product_standard_margin/views/view_product_template.xml
odoo_addon_product_standard_margin-18.0.1.1.0.1.dist-info/METADATA
odoo_addon_product_standard_margin-18.0.1.1.0.1.dist-info/WHEEL
odoo_addon_product_standard_margin-18.0.1.1.0.1.dist-info/top_level.txt
odoo_addon_product_standard_margin-18.0.1.1.0.1.dist-info/RECORD
